MtySdk/Heshitaoli.py
MtySdk/MtyApi.py
MtySdk/__init__.py
MtySdk/run.py
MtySdk/uploadfile.py
MtySdk-0.1.3.dist-info/METADATA
MtySdk-0.1.3.dist-info/WHEEL
MtySdk-0.1.3.dist-info/top_level.txt
MtySdk-0.1.3.dist-info/RECORD
