Metadata-Version: 2.1
Name: MtySdk
Version: 0.1.3
Summary: This is a demo
Home-page: https://gitee.com/hexingchi/mty-sdk.git
Author: Credi He
Author-email: 17316365004@sina.cn
License: UNKNOWN
Platform: UNKNOWN
Classifier: Programming Language :: Python :: 3
Classifier: License :: OSI Approved :: MIT License
Classifier: Operating System :: OS Independent
